gloce/__init__.py
gloce/area.py
gloce/func.py
gloce/gc.py
gloce/interpolation.py
gloce/resample.py
gloce-2.3.dist-info/LICENSE
gloce-2.3.dist-info/METADATA
gloce-2.3.dist-info/WHEEL
gloce-2.3.dist-info/top_level.txt
gloce-2.3.dist-info/RECORD
