Metadata-Version: 2.2
Name: gloce
Version: 2.3
Summary: A package for global change ecology studies
Home-page: https://github.com/zhu3210/gloce
Author: Lei Zhu
Author-email: lzhu_1999@163.com
Project-URL: Bug Tracker, https://github.com/zhu3210/gloce
Classifier: Programming Language :: Python :: 3
Classifier: License :: OSI Approved :: MIT License
Classifier: Operating System :: OS Independent
Requires-Python: >=3.6
License-File: LICENSE
